taskmesh/__init__.py
taskmesh/config.py
taskmesh/core.py
taskmesh/providers/__init__.py
taskmesh/providers/core.py
taskmesh/providers/aws/__init__.py
taskmesh/providers/aws/provider.py
taskmesh/providers/gcp/__init__.py
taskmesh/providers/gcp/provider.py
taskmesh-0.0.1.dist-info/LICENSE
taskmesh-0.0.1.dist-info/METADATA
taskmesh-0.0.1.dist-info/WHEEL
taskmesh-0.0.1.dist-info/top_level.txt
taskmesh-0.0.1.dist-info/RECORD
