Metadata-Version: 2.2
Name: taskmesh
Version: 0.0.1
Summary: TaskMesh is a cloud-agnostic task processing framework starting with Google Cloud Pub/Sub.
Author-email: "Amrit K. Chhetri" <kshetriamrit@gmail.com>
License: GNU
Project-URL: Homepage, https://github.com/bunkdeath/taskmesh
Project-URL: Documentation, https://github.com/bunkdeath/taskmesh/wiki
Project-URL: Source, https://github.com/bunkdeath/taskmesh
Project-URL: Issues, https://github.com/bunkdeath/taskmesh/issues
Keywords: task queue,pubsub,sqs,gcp,aws,cloud,distributed processing
Classifier: Development Status :: 3 - Alpha
Classifier: Intended Audience :: Developers
Classifier: License :: OSI Approved :: GNU General Public License v3 (GPLv3)
Classifier: Programming Language :: Python :: 3
Classifier: Programming Language :: Python :: 3.8
Classifier: Programming Language :: Python :: 3.9
Classifier: Programming Language :: Python :: 3.10
Classifier: Programming Language :: Python :: 3.11
Classifier: Topic :: Software Development :: Libraries :: Python Modules
License-File: LICENSE
Requires-Dist: boto3==1.37.9
Requires-Dist: google-cloud-pubsub==2.28.0
Requires-Dist: python-dotenv==1.0.1
Provides-Extra: dev
Requires-Dist: pytest; extra == "dev"
Requires-Dist: black; extra == "dev"
Requires-Dist: flake8; extra == "dev"
Requires-Dist: mypy; extra == "dev"
Requires-Dist: pre-commit; extra == "dev"
